LICENSE.txt
README.md
setup.cfg
setup.py
captpyshell/__init__.py
captpyshell/shell.py
captpyshell.egg-info/PKG-INFO
captpyshell.egg-info/SOURCES.txt
captpyshell.egg-info/dependency_links.txt
captpyshell.egg-info/top_level.txt