Metadata-Version: 2.1
Name: captpyshell
Version: 1.0
Summary: python debugger, inject code into python prosses
Home-page: https://github.com/kapten-kaizo/pyshell/
Download-URL: https://github.com/kapten-kaizo/captpyshell/archive/refs/tags/V1.tar.gz
Author: kapten-kaizo
Author-email: cyber2687@gmail.com
License: MIT
Keywords: SOME,MEANINGFULL,KEYWORDS
Classifier: Development Status :: 3 - Alpha
Classifier: Intended Audience :: Developers
Classifier: Topic :: Software Development :: Build Tools
Classifier: License :: OSI Approved :: MIT License
Classifier: Programming Language :: Python :: 3.9
License-File: LICENSE.txt
